dlup/__init__.py
dlup/_background.pyi
dlup/_background.so
dlup/_exceptions.py
dlup/_geometry.pyi
dlup/_geometry.so
dlup/_image.py
dlup/_libtiff_tiff_writer.pyi
dlup/_libtiff_tiff_writer.so
dlup/_region.py
dlup/_types.py
dlup/annotations/__init__.py
dlup/annotations/exporters/__init__.py
dlup/annotations/exporters/dlup_xml.py
dlup/annotations/exporters/geojson.py
dlup/annotations/exporters/slidescore_tsv.py
dlup/annotations/importers/__init__.py
dlup/annotations/importers/asap_xml.py
dlup/annotations/importers/darwin_json.py
dlup/annotations/importers/dlup_xml.py
dlup/annotations/importers/geojson.py
dlup/annotations/importers/halo_xml.py
dlup/annotations/importers/slidescore_tsv.py
dlup/annotations/tags.py
dlup/backends/__init__.py
dlup/backends/common.py
dlup/backends/fastslide_backend.py
dlup/backends/fimage_backend.py
dlup/backends/openslide_backend.py
dlup/backends/tifffile_backend.py
dlup/background.py
dlup/data/__init__.py
dlup/data/dataset.py
dlup/geometry/__init__.py
dlup/geometry/marching_squares.so
dlup/geometry/measure.py
dlup/logging.py
dlup/py.typed
dlup/tiling.py
dlup/tools.py
dlup/utils/__init__.py
dlup/utils/annotations_utils.py
dlup/utils/backends.py
dlup/utils/geometry_xml.py
dlup/utils/image.py
dlup/utils/imports.py
dlup/utils/schemas/dlup_schema_v1.0.xsd
dlup/utils/schemas/generated/__init__.py
dlup/utils/schemas/generated/dlup_schema_v1_0.py
dlup/utils/tifffile_utils.py
dlup/writers.py
dlup-0.8.0.dist-info/WHEEL
dlup-0.8.0.dist-info/METADATA
dlup-0.8.0.dist-info/RECORD
