Metadata-Version: 2.1
Name: dlup
Author: dlup contributors
Author-email: j.teuwen@nki.nl
Home-page: https://github.com/NKI-AI/dlup
License: Apache-2.0
Summary: Deep Learning Utilities for Pathology
Requires-Python: >=3.10
Requires-Dist: fastslide
Requires-Dist: fimage-python
Requires-Dist: openslide-python
Requires-Dist: numpy
Requires-Dist: packaging
Requires-Dist: pillow
Requires-Dist: shapely
Requires-Dist: tifffile
Requires-Dist: xsdata
Version: 0.8.0
